README.md
setup.py
doculabs/__init__.py
doculabs/samon/__init__.py
doculabs/samon/constants.py
doculabs/samon/elements.py
doculabs/samon/environment.py
doculabs/samon/exceptions.py
doculabs/samon/expressions.py
doculabs/samon/loaders.py
doculabs/samon/registry.py
doculabs/samon/template.py
doculabs/samon/parser/__init__.py
doculabs/samon/parser/json.py
doculabs/samon/parser/xml.py
samon.egg-info/PKG-INFO
samon.egg-info/SOURCES.txt
samon.egg-info/dependency_links.txt
samon.egg-info/requires.txt
samon.egg-info/top_level.txt
tests/__init__.py
tests/mock.py
tests/test_dict_parser.py
tests/test_elements.py
tests/test_environment.py
tests/test_expressions.py
tests/test_loaders.py
tests/test_parser.py
tests/test_registry.py
tests/test_template.py