Metadata-Version: 1.1
Name: samon
Version: 0.4
Summary: Samon (salmon) XML based templating engine
Home-page: https://github.com/doculabs/samon
Author: Bence Lovas
Author-email: lovas.bence@doculabs.io
License: BSD
Download-URL: https://github.com/doculabs/samon
Platform: UNKNOWN
